LICENSE
README.rst
setup.py
fixie_creds/__init__.py
fixie_creds/cache.py
fixie_creds/environ.py
fixie_creds/handlers.py
fixie_creds.egg-info/PKG-INFO
fixie_creds.egg-info/SOURCES.txt
fixie_creds.egg-info/dependency_links.txt
fixie_creds.egg-info/not-zip-safe
fixie_creds.egg-info/top_level.txt