Metadata-Version: 1.1
Name: fixie-creds
Version: 0.0.1
Summary: A Cyclus credentialing service
Home-page: https://github.com/ergs/fixie-creds
Author: The ERGS developers
Author-email: ergsonomic@googlegroups.com
License: BSD 3-clause
Download-URL: https://github.com/ergs/fixie-creds/zipball/0.0.1
Platform: UNKNOWN
Classifier: License :: OSI Approved
Classifier: Intended Audience :: Developers
Classifier: Programming Language :: Python
Classifier: Topic :: Utilities
